tangent_client/__init__.py
tangent_client/_version.py
tangent_client/client.py
tangent_client/logging.py
tangent_client/logging.yaml
tangent_client/utils/__init__.py
tangent_client-0.1.0.dist-info/METADATA
tangent_client-0.1.0.dist-info/WHEEL
tangent_client-0.1.0.dist-info/RECORD
