Metadata-Version: 2.3
Name: tangent-client
Version: 0.1.0
Summary: Python Client for Tangent Works.
Author: Tangent Works
Requires-Python: >=3.10
Classifier: Programming Language :: Python :: 3
Classifier: Programming Language :: Python :: 3.10
Classifier: Programming Language :: Python :: 3.11
Classifier: Programming Language :: Python :: 3.12
Classifier: Programming Language :: Python :: 3.13
Requires-Dist: libranet-logging (>=1.5.2)
Requires-Dist: pandas (>=2.2.1)
Requires-Dist: requests (>=2.31.0)
Project-URL: Documentation, https://docs.tangent.works/
Project-URL: Homepage, https://tangent.works/
